aliyunsdksae/__init__.py
aliyunsdksae/endpoint.py
aliyunsdksae/request/__init__.py
aliyunsdksae/request/v20190506/AbortAndRollbackChangeOrderRequest.py
aliyunsdksae/request/v20190506/AbortChangeOrderRequest.py
aliyunsdksae/request/v20190506/BatchStartApplicationsRequest.py
aliyunsdksae/request/v20190506/BatchStopApplicationsRequest.py
aliyunsdksae/request/v20190506/BindSlbRequest.py
aliyunsdksae/request/v20190506/ConfirmPipelineBatchRequest.py
aliyunsdksae/request/v20190506/CreateApplicationRequest.py
aliyunsdksae/request/v20190506/CreateApplicationScalingRuleRequest.py
aliyunsdksae/request/v20190506/CreateConfigMapRequest.py
aliyunsdksae/request/v20190506/CreateGreyTagRouteRequest.py
aliyunsdksae/request/v20190506/CreateIngressRequest.py
aliyunsdksae/request/v20190506/CreateJobRequest.py
aliyunsdksae/request/v20190506/CreateNamespaceRequest.py
aliyunsdksae/request/v20190506/CreateSecretRequest.py
aliyunsdksae/request/v20190506/DeleteApplicationRequest.py
aliyunsdksae/request/v20190506/DeleteApplicationScalingRuleRequest.py
aliyunsdksae/request/v20190506/DeleteConfigMapRequest.py
aliyunsdksae/request/v20190506/DeleteGreyTagRouteRequest.py
aliyunsdksae/request/v20190506/DeleteHistoryJobRequest.py
aliyunsdksae/request/v20190506/DeleteIngressRequest.py
aliyunsdksae/request/v20190506/DeleteJobRequest.py
aliyunsdksae/request/v20190506/DeleteNamespaceRequest.py
aliyunsdksae/request/v20190506/DeleteSecretRequest.py
aliyunsdksae/request/v20190506/DeployApplicationRequest.py
aliyunsdksae/request/v20190506/DescribeAppServiceDetailRequest.py
aliyunsdksae/request/v20190506/DescribeApplicationConfigRequest.py
aliyunsdksae/request/v20190506/DescribeApplicationGroupsRequest.py
aliyunsdksae/request/v20190506/DescribeApplicationImageRequest.py
aliyunsdksae/request/v20190506/DescribeApplicationInstancesRequest.py
aliyunsdksae/request/v20190506/DescribeApplicationScalingRuleRequest.py
aliyunsdksae/request/v20190506/DescribeApplicationScalingRulesRequest.py
aliyun_python_sdk_sae-1.22.16.dist-info/LICENSE
aliyun_python_sdk_sae-1.22.16.dist-info/METADATA
aliyun_python_sdk_sae-1.22.16.dist-info/WHEEL
aliyun_python_sdk_sae-1.22.16.dist-info/top_level.txt
aliyun_python_sdk_sae-1.22.16.dist-info/RECORD
